setup.py
zmop/RSAUtil.py
zmop/WebUtil.py
zmop/ZmopClient.py
zmop/__init__.py
zmop.egg-info/PKG-INFO
zmop.egg-info/SOURCES.txt
zmop.egg-info/dependency_links.txt
zmop.egg-info/top_level.txt
zmop.egg-info/zip-safe
zmop/request/ZhimaAuthEngineMultiauthRequest.py
zmop/request/ZhimaAuthEngineOrganizationauthRequest.py
zmop/request/ZhimaAuthEngineProtocolRequest.py
zmop/request/ZhimaAuthEngineSmsauthRequest.py
zmop/request/ZhimaAuthFaceInitRequest.py
zmop/request/ZhimaAuthFaceVerifyRequest.py
zmop/request/ZhimaAuthInfoAuthorizeRequest.py
zmop/request/ZhimaAuthInfoAuthqueryRequest.py
zmop/request/ZhimaAuthInfoFreezeRequest.py
zmop/request/ZhimaAuthZhimaCustCertifyInitialRequest.py
zmop/request/ZhimaCreditAntifraudIntegrationQueryRequest.py
zmop/request/ZhimaCreditAntifraudRiskListRequest.py
zmop/request/ZhimaCreditAntifraudScoreGetRequest.py
zmop/request/ZhimaCreditAntifraudVerifyRequest.py
zmop/request/ZhimaCreditBqsDefaultscoreQueryRequest.py
zmop/request/ZhimaCreditCardLimitGetRequest.py
zmop/request/ZhimaCreditCardPermitRequest.py
zmop/request/ZhimaCreditCardVerifyRequest.py
zmop/request/ZhimaCreditCollectionSupportRequest.py
zmop/request/ZhimaCreditContactAnalyzeQueryRequest.py
zmop/request/ZhimaCreditContactGetRequest.py
zmop/request/ZhimaCreditDasGetRequest.py
zmop/request/ZhimaCreditDriverVerifyRequest.py
zmop/request/ZhimaCreditEpAssetFreezeGetRequest.py
zmop/request/ZhimaCreditEpAssetSealGetRequest.py
zmop/request/ZhimaCreditEpBriefScoreQueryRequest.py
zmop/request/ZhimaCreditEpCaseSeriesQueryRequest.py
zmop/request/ZhimaCreditEpCloudatlasApplyRequest.py
zmop/request/ZhimaCreditEpCloudatlasGetRequest.py
zmop/request/ZhimaCreditEpCommercialPunishmentQueryRequest.py
zmop/request/ZhimaCreditEpContactNameGetRequest.py
zmop/request/ZhimaCreditEpContactPhoneGetRequest.py
zmop/request/ZhimaCreditEpEnvprotectionPunishmentQueryRequest.py
zmop/request/ZhimaCreditEpIndividualScoreGetRequest.py
zmop/request/ZhimaCreditEpInfoGetRequest.py
zmop/request/ZhimaCreditEpLawsuitDetailGetRequest.py
zmop/request/ZhimaCreditEpLawsuitRecordGetRequest.py
zmop/request/ZhimaCreditEpNegativeQueryRequest.py
