Metadata-Version: 1.1
Name: zmop
Version: 1.0.2
Summary: 芝麻信用sdk
Home-page: https://b.zmxy.com.cn/technology/sdkDownload.htm
Author: your_name
Author-email: youremail@email.com
License: MIT
Platform: UNKNOWN
Classifier: License :: OSI Approved :: MIT License
Classifier: Programming Language :: Python
Classifier: Intended Audience :: Developers
Classifier: Operating System :: OS Independent
